intelliagent/__init__.py
intelliagent/py.typed
intelliagent/version.py
intelliagent-0.1.1.dist-info/METADATA
intelliagent-0.1.1.dist-info/WHEEL
intelliagent-0.1.1.dist-info/top_level.txt
intelliagent-0.1.1.dist-info/RECORD
